{
  "seviervillelandclearing.com": {
    "keywords": {
      "land clearing Sevierville TN": {
        "rank": null,
        "previousRank": null,
        "change": null,
        "competitors": {},
        "checkedAt": "2026-05-03T14:10:12.537Z"
      },
      "forestry mulching Sevierville TN": {
        "rank": null,
        "previousRank": null,
        "change": null,
        "competitors": {},
        "checkedAt": "2026-05-03T14:10:17.678Z"
      },
      "lot clearing Sevierville TN": {
        "rank": null,
        "previousRank": null,
        "change": null,
        "competitors": {},
        "checkedAt": "2026-05-03T14:10:22.780Z"
      },
      "land clearing Pigeon Forge TN": {
        "rank": null,
        "previousRank": null,
        "change": null,
        "competitors": {},
        "checkedAt": "2026-05-03T14:10:27.798Z"
      },
      "land clearing Gatlinburg TN": {
        "rank": null,
        "previousRank": null,
        "change": null,
        "competitors": {},
        "checkedAt": "2026-05-03T14:10:32.972Z"
      },
      "land clearing Sevier County TN": {
        "rank": null,
        "previousRank": null,
        "change": null,
        "competitors": {},
        "checkedAt": "2026-05-03T14:10:38.204Z"
      },
      "brush clearing Sevier County TN": {
        "rank": null,
        "previousRank": null,
        "change": null,
        "competitors": {},
        "checkedAt": "2026-05-03T14:10:43.305Z"
      },
      "cabin lot clearing Smoky Mountains TN": {
        "rank": null,
        "previousRank": null,
        "change": null,
        "competitors": {},
        "checkedAt": "2026-05-03T14:10:48.510Z"
      },
      "site preparation Sevierville TN": {
        "rank": null,
        "previousRank": null,
        "change": null,
        "competitors": {},
        "checkedAt": "2026-05-03T14:10:53.567Z"
      },
      "bush hogging Sevierville TN": {
        "rank": null,
        "previousRank": null,
        "change": null,
        "competitors": {},
        "checkedAt": "2026-05-03T14:10:58.575Z"
      }
    },
    "screenshots": []
  },
  "knoxvillelandclearing.com": {
    "keywords": {
      "land clearing Knoxville TN": {
        "rank": null,
        "previousRank": null,
        "change": null,
        "competitors": {},
        "checkedAt": "2026-05-03T14:11:03.664Z"
      },
      "forestry mulching Knoxville TN": {
        "rank": null,
        "previousRank": null,
        "change": null,
        "competitors": {},
        "checkedAt": "2026-05-03T14:11:08.850Z"
      },
      "lot clearing Knoxville TN": {
        "rank": null,
        "previousRank": null,
        "change": null,
        "competitors": {},
        "checkedAt": "2026-05-03T14:11:13.885Z"
      },
      "land clearing Maryville TN": {
        "rank": null,
        "previousRank": null,
        "change": null,
        "competitors": {},
        "checkedAt": "2026-05-03T14:11:18.907Z"
      },
      "land clearing Oak Ridge TN": {
        "rank": null,
        "previousRank": null,
        "change": null,
        "competitors": {},
        "checkedAt": "2026-05-03T14:11:24.137Z"
      },
      "land clearing Farragut TN": {
        "rank": null,
        "previousRank": null,
        "change": null,
        "competitors": {},
        "checkedAt": "2026-05-03T14:11:29.404Z"
      },
      "brush clearing Knoxville TN": {
        "rank": null,
        "previousRank": null,
        "change": null,
        "competitors": {},
        "checkedAt": "2026-05-03T14:11:34.427Z"
      },
      "site preparation Knoxville TN": {
        "rank": null,
        "previousRank": null,
        "change": null,
        "competitors": {},
        "checkedAt": "2026-05-03T14:11:39.694Z"
      },
      "land clearing Blount County TN": {
        "rank": null,
        "previousRank": null,
        "change": null,
        "competitors": {},
        "checkedAt": "2026-05-03T14:11:44.766Z"
      },
      "land clearing cost Knoxville TN": {
        "rank": null,
        "previousRank": null,
        "change": null,
        "competitors": {},
        "checkedAt": "2026-05-03T14:11:50.040Z"
      }
    },
    "screenshots": []
  }
}