{
  "seviervillelandclearing.com": {
    "keywords": {
      "land clearing Sevierville TN": {
        "rank": null,
        "previousRank": null,
        "change": null,
        "competitors": {},
        "checkedAt": "2026-05-26T16:39:32.696Z"
      },
      "forestry mulching Sevierville TN": {
        "rank": null,
        "previousRank": null,
        "change": null,
        "competitors": {},
        "checkedAt": "2026-05-26T16:39:37.971Z"
      },
      "lot clearing Sevierville TN": {
        "rank": null,
        "previousRank": null,
        "change": null,
        "competitors": {},
        "checkedAt": "2026-05-26T16:39:42.995Z"
      },
      "land clearing Pigeon Forge TN": {
        "rank": null,
        "previousRank": null,
        "change": null,
        "competitors": {},
        "checkedAt": "2026-05-26T16:39:47.987Z"
      },
      "land clearing Gatlinburg TN": {
        "rank": null,
        "previousRank": null,
        "change": null,
        "competitors": {},
        "checkedAt": "2026-05-26T16:39:53.258Z"
      },
      "land clearing Sevier County TN": {
        "rank": null,
        "previousRank": null,
        "change": null,
        "competitors": {},
        "checkedAt": "2026-05-26T16:39:58.376Z"
      },
      "brush clearing Sevier County TN": {
        "rank": null,
        "previousRank": null,
        "change": null,
        "competitors": {},
        "checkedAt": "2026-05-26T16:40:03.587Z"
      },
      "cabin lot clearing Smoky Mountains TN": {
        "rank": null,
        "previousRank": null,
        "change": null,
        "competitors": {},
        "checkedAt": "2026-05-26T16:40:08.618Z"
      },
      "site preparation Sevierville TN": {
        "rank": null,
        "previousRank": null,
        "change": null,
        "competitors": {},
        "checkedAt": "2026-05-26T16:40:13.646Z"
      },
      "bush hogging Sevierville TN": {
        "rank": null,
        "previousRank": null,
        "change": null,
        "competitors": {},
        "checkedAt": "2026-05-26T16:40:18.669Z"
      }
    },
    "screenshots": []
  },
  "knoxvillelandclearing.com": {
    "keywords": {
      "land clearing Knoxville TN": {
        "rank": null,
        "previousRank": null,
        "change": null,
        "competitors": {},
        "checkedAt": "2026-05-26T16:40:23.639Z"
      },
      "forestry mulching Knoxville TN": {
        "rank": null,
        "previousRank": null,
        "change": null,
        "competitors": {},
        "checkedAt": "2026-05-26T16:40:28.870Z"
      },
      "lot clearing Knoxville TN": {
        "rank": null,
        "previousRank": null,
        "change": null,
        "competitors": {},
        "checkedAt": "2026-05-26T16:40:34.148Z"
      },
      "land clearing Maryville TN": {
        "rank": null,
        "previousRank": null,
        "change": null,
        "competitors": {},
        "checkedAt": "2026-05-26T16:40:39.261Z"
      },
      "land clearing Oak Ridge TN": {
        "rank": null,
        "previousRank": null,
        "change": null,
        "competitors": {},
        "checkedAt": "2026-05-26T16:40:44.399Z"
      },
      "land clearing Farragut TN": {
        "rank": null,
        "previousRank": null,
        "change": null,
        "competitors": {},
        "checkedAt": "2026-05-26T16:40:49.440Z"
      },
      "brush clearing Knoxville TN": {
        "rank": null,
        "previousRank": null,
        "change": null,
        "competitors": {},
        "checkedAt": "2026-05-26T16:40:54.557Z"
      },
      "site preparation Knoxville TN": {
        "rank": null,
        "previousRank": null,
        "change": null,
        "competitors": {},
        "checkedAt": "2026-05-26T16:40:59.599Z"
      },
      "land clearing Blount County TN": {
        "rank": null,
        "previousRank": null,
        "change": null,
        "competitors": {},
        "checkedAt": "2026-05-26T16:41:04.711Z"
      },
      "land clearing cost Knoxville TN": {
        "rank": null,
        "previousRank": null,
        "change": null,
        "competitors": {},
        "checkedAt": "2026-05-26T16:41:09.824Z"
      }
    },
    "screenshots": []
  }
}